setup.py
dm/__init__.py
dm.zopepatches.zclasses.egg-info/PKG-INFO
dm.zopepatches.zclasses.egg-info/SOURCES.txt
dm.zopepatches.zclasses.egg-info/dependency_links.txt
dm.zopepatches.zclasses.egg-info/namespace_packages.txt
dm.zopepatches.zclasses.egg-info/not-zip-safe
dm.zopepatches.zclasses.egg-info/top_level.txt
dm/zopepatches/__init__.py
dm/zopepatches/zclasses/27.fs
dm/zopepatches/zclasses/27.txt
dm/zopepatches/zclasses/Basic.py
dm/zopepatches/zclasses/Factory.py
dm/zopepatches/zclasses/Method.py
dm/zopepatches/zclasses/ObjectManager.py
dm/zopepatches/zclasses/Property.py
dm/zopepatches/zclasses/README.txt
dm/zopepatches/zclasses/VERSION.txt
dm/zopepatches/zclasses/ZClass.py
dm/zopepatches/zclasses/ZClass.txt
dm/zopepatches/zclasses/ZClassOwner.py
dm/zopepatches/zclasses/__init__.py
dm/zopepatches/zclasses/_pmc.py
dm/zopepatches/zclasses/_pmc.txt
dm/zopepatches/zclasses/class.gif
dm/zopepatches/zclasses/methods.gif
dm/zopepatches/zclasses/propertysheets.gif
dm/zopepatches/zclasses/testZClasses.py
dm/zopepatches/zclasses/tests.py
dm/zopepatches/zclasses/doc/zclasses.html
dm/zopepatches/zclasses/dtml/addCommonSheet.dtml
dm/zopepatches/zclasses/dtml/addFactory.dtml
dm/zopepatches/zclasses/dtml/addIcon.dtml
dm/zopepatches/zclasses/dtml/addProduct.dtml
dm/zopepatches/zclasses/dtml/addPropertyInterface.dtml
dm/zopepatches/zclasses/dtml/addZClass.dtml
dm/zopepatches/zclasses/dtml/advanced.dtml
dm/zopepatches/zclasses/dtml/classPermissions.dtml
dm/zopepatches/zclasses/dtml/contents.dtml
dm/zopepatches/zclasses/dtml/distributionView.dtml
dm/zopepatches/zclasses/dtml/itemProp.dtml
dm/zopepatches/zclasses/dtml/methodAccess.dtml
dm/zopepatches/zclasses/dtml/subobjects.dtml
dm/zopepatches/zclasses/dtml/views.dtml
dm/zopepatches/zclasses/www/factory.gif