Metadata-Version: 1.0
Name: dm.zopepatches.zclasses
Version: 0.1.1
Summary: Through the Web application development without deep programming skills (former ZClasses functionality in the Zope core).
Home-page: http://pypi.python.org/dm.zopepatches.zclasses
Author: Dieter Maurer
Author-email: dieter@handshake.de
License: BSD
Keywords: application development menu web
Platform: UNKNOWN
Classifier: Development Status :: 3 - Alpha
Classifier: Intended Audience :: Developers
Classifier: License :: OSI Approved :: BSD License
Classifier: Framework :: Zope2
Classifier: Operating System :: OS Independent
Classifier: Programming Language :: Python
Classifier: Topic :: Utilities
